aixtools/__init__.py
aixtools/_version.py
aixtools/app.py
aixtools/chainlit.md
aixtools/context.py
aixtools/.chainlit/config.toml
aixtools/.chainlit/translations/bn.json
aixtools/.chainlit/translations/en-US.json
aixtools/.chainlit/translations/gu.json
aixtools/.chainlit/translations/he-IL.json
aixtools/.chainlit/translations/hi.json
aixtools/.chainlit/translations/ja.json
aixtools/.chainlit/translations/kn.json
aixtools/.chainlit/translations/ml.json
aixtools/.chainlit/translations/mr.json
aixtools/.chainlit/translations/nl.json
aixtools/.chainlit/translations/ta.json
aixtools/.chainlit/translations/te.json
aixtools/.chainlit/translations/zh-CN.json
aixtools/a2a/__init__.py
aixtools/a2a/app.py
aixtools/a2a/auth_middleware.py
aixtools/a2a/auth_push_notification_sender.py
aixtools/a2a/context_middleware.py
aixtools/a2a/utils.py
aixtools/a2a/google_sdk/__init__.py
aixtools/a2a/google_sdk/remote_agent_connection.py
aixtools/a2a/google_sdk/utils.py
aixtools/a2a/google_sdk/pydantic_ai_adapter/__init__.py
aixtools/a2a/google_sdk/pydantic_ai_adapter/agent_executor.py
aixtools/a2a/google_sdk/pydantic_ai_adapter/storage.py
aixtools/a2a/google_sdk/pydantic_ai_adapter/types.py
aixtools/a2a/google_sdk/pydantic_ai_adapter/db/__init__.py
aixtools/a2a/google_sdk/pydantic_ai_adapter/db/models.py
aixtools/a2a/google_sdk/pydantic_ai_adapter/db/repository.py
aixtools/a2a/google_sdk/pydantic_ai_adapter/db/storage.py
aixtools/a2a/google_sdk/store/__init__.py
aixtools/a2a/google_sdk/store/alembic.ini
aixtools/a2a/google_sdk/store/config.py
aixtools/a2a/google_sdk/store/ensure_database.py
aixtools/a2a/google_sdk/store/models.py
aixtools/a2a/google_sdk/store/migrations/env.py
aixtools/a2a/google_sdk/store/migrations/script.py.mako
aixtools/a2a/google_sdk/store/migrations/versions/027244bea7df_push_notifications_config.py
aixtools/a2a/google_sdk/store/migrations/versions/1ee8d8ef55f4_pydantic_message_history.py
aixtools-0.10.1.dist-info/METADATA
aixtools-0.10.1.dist-info/WHEEL
aixtools-0.10.1.dist-info/entry_points.txt
aixtools-0.10.1.dist-info/top_level.txt
aixtools-0.10.1.dist-info/RECORD
