Metadata-Version: 2.4
Name: aixtools
Version: 0.10.1
Summary: Tools for AI exploration and debugging
Requires-Python: >=3.11.2
Requires-Dist: a2a-sdk[postgresql]>=0.3.3
Requires-Dist: alembic>=1.17.1
Requires-Dist: cachebox>=5.0.1
Requires-Dist: chainlit>=2.5.5
Requires-Dist: colorlog>=6.9.0
Requires-Dist: fasta2a>=0.6.0
Requires-Dist: fastmcp>=2.14.0
Requires-Dist: hvac>=2.3.0
Requires-Dist: ipykernel>=6.29.5
Requires-Dist: jupyterlab>=4.4.3
Requires-Dist: langchain-chroma>=0.2.3
Requires-Dist: langchain-ollama>=0.3.2
Requires-Dist: langchain-openai>=0.3.14
Requires-Dist: markitdown[docx,pdf,pptx,xls,xlsx]>=0.1.3
Requires-Dist: mcp>=1.23.3
Requires-Dist: msal>=1.29.0
Requires-Dist: msal-extensions>=1.1.0
Requires-Dist: mypy>=1.18.2
Requires-Dist: nest_asyncio>=1.6.0
Requires-Dist: odfpy>=1.4.1
Requires-Dist: openpyxl>=3.1.5
Requires-Dist: pandas>=2.2.3
Requires-Dist: podkit>=0.7.1
Requires-Dist: psycopg2-binary>=2.9.11
Requires-Dist: pydantic-ai>=1.44.0
Requires-Dist: pyjwt>=2.10.1
Requires-Dist: pylint>=3.3.7
Requires-Dist: python-frontmatter>=1.1.0
Requires-Dist: rich>=14.0.0
Requires-Dist: ruff>=0.11.6
Requires-Dist: sqlalchemy>=2.0.44
Requires-Dist: streamlit>=1.44.1
Requires-Dist: tiktoken>=0.9.0
Requires-Dist: watchdog>=6.0.0
Requires-Dist: xlrd>=2.0.2
Provides-Extra: test
Requires-Dist: pyyaml; extra == "test"
Provides-Extra: feature
Requires-Dist: logfire; extra == "feature"
